CHANGELOG.md
LICENSE
MANIFEST.in
README.md
requirements.txt
setup.py
docs/Makefile
docs/api.rst
docs/changelog.rst
docs/conf.py
docs/index.rst
docs/installation.rst
docs/license.rst
docs/make.bat
kua/__init__.py
kua/routes.py
kua.egg-info/PKG-INFO
kua.egg-info/SOURCES.txt
kua.egg-info/dependency_links.txt
kua.egg-info/not-zip-safe
kua.egg-info/top_level.txt
tests/__init__.py
tests/tests_routes.py